imagenet_c/__init__.py
imagenet_c/corruptions.py
imagenet_c-0.0.3.dist-info/METADATA
imagenet_c-0.0.3.dist-info/WHEEL
imagenet_c-0.0.3.dist-info/top_level.txt
imagenet_c-0.0.3.dist-info/RECORD
