Metadata-Version: 2.1
Name: imagenet-c
Version: 0.0.3
Summary: Access to ImageNet-C corruption functions
Home-page: https://github.com/hendrycks/robustness/tree/master/ImageNet-C/imagenet_c
Author: Dan Hendrycks
Author-email: hendrycks@berkeley.edu
License: UNKNOWN
Platform: UNKNOWN
Classifier: Programming Language :: Python :: 3
Classifier: License :: OSI Approved :: MIT License
Classifier: Operating System :: OS Independent
Requires-Dist: wand (~=0.4)
Requires-Dist: opencv-python (~=3.4)
